examples/example_1.py
examples/example_2.py
examples/example_3.py
examples/example_4.py
scoretree/__init__.py
scoretree/core/__init__.py
scoretree/core/formatter.py
scoretree/core/scores.py
scoretree/core/tree.py
scoretree/tests/__init__.py
scoretree/tests/test_formatter.py
scoretree/tests/test_scores.py
scoretree/tests/test_tree.py
scoretree-1.1.0.dist-info/LICENSE
scoretree-1.1.0.dist-info/METADATA
scoretree-1.1.0.dist-info/WHEEL
scoretree-1.1.0.dist-info/top_level.txt
scoretree-1.1.0.dist-info/RECORD
