Metadata-Version: 2.1
Name: scoretree
Version: 1.1.0
Summary: Easy to use, multi-level grade weighting system
Author-email: Paulo Sanchez <dev.szblzpaulo@gmail.com>
Maintainer-email: Paulo Sanchez <dev.szblzpaulo@gmail.com>
License: GNU AFFERO GENERAL PUBLIC LICENSE
Project-URL: Homepage, https://github.com/erlete/scoretree
Project-URL: Bug Tracker, https://github.com/erlete/scoretree/issues
Classifier: Intended Audience :: Developers
Classifier: Programming Language :: Python :: 3
Classifier: License :: OSI Approved :: GNU General Public License v3 (GPLv3)
Classifier: Operating System :: OS Independent
Requires-Python: >=3.10.0
License-File: LICENSE
Requires-Dist: colorama ==0.4.6
Requires-Dist: types-colorama ==0.4.15.12
Provides-Extra: test
Requires-Dist: pytest ==7.4.3 ; extra == 'test'
Requires-Dist: pytest-cov ==4.1.0 ; extra == 'test'
Requires-Dist: pytest-html ==4.1.1 ; extra == 'test'
Requires-Dist: pycodestyle ==2.11.1 ; extra == 'test'
Requires-Dist: pydocstyle ==6.3.0 ; extra == 'test'
Requires-Dist: mypy ==1.7.0 ; extra == 'test'
Requires-Dist: flake8 ==6.1.0 ; extra == 'test'
